netdiscover/__init__.py
netdiscover/netdiscover.py
python_netdiscover-0.3.0.dist-info/AUTHORS.rst
python_netdiscover-0.3.0.dist-info/LICENSE
python_netdiscover-0.3.0.dist-info/METADATA
python_netdiscover-0.3.0.dist-info/WHEEL
python_netdiscover-0.3.0.dist-info/top_level.txt
python_netdiscover-0.3.0.dist-info/RECORD
