Metadata-Version: 2.1
Name: python-netdiscover
Version: 0.3.0
Summary: python-netdiscover is a simple wrapper for the netdiscover reconnaissance tool
Home-page: https://github.com/MrSuicideParrot/python-netdiscover
Author: André Cirne
Author-email: ancirne@gmail.com
License: GNU General Public License v3
Keywords: network,netdiscover,arpscanner,sysadmin
Classifier: Development Status :: 2 - Pre-Alpha
Classifier: Intended Audience :: System Administrators
Classifier: Topic :: System :: Monitoring
Classifier: Topic :: System :: Networking
Classifier: Topic :: System :: Networking :: Firewalls
Classifier: Topic :: System :: Networking :: Monitoring
Classifier: License :: OSI Approved :: GNU General Public License v3 (GPLv3)
Classifier: Natural Language :: English
Classifier: Programming Language :: Python :: 2
Classifier: Programming Language :: Python :: 2.7
Classifier: Programming Language :: Python :: 3
Classifier: Programming Language :: Python :: 3.4
Classifier: Programming Language :: Python :: 3.5
Classifier: Programming Language :: Python :: 3.6
Classifier: Programming Language :: Python :: 3.7
License-File: LICENSE
License-File: AUTHORS.rst
